README.rst
setup.py
zy_tools/__init__.py
zy_tools/aliyun_log_query.py
zy_tools/beautiful_output_dict.py
zy_tools/data_fix.py
zy_tools/get_sorted_un_duplicated_list.py
zy_tools/read_file.py
zy_tools/send_ent_we_chat_msg.py
zy_tools/send_msg_to_queue.py
zy_tools/ssh_connection_mongo.py
zy_tools/sync_open_search.py
zy_tools.egg-info/PKG-INFO
zy_tools.egg-info/SOURCES.txt
zy_tools.egg-info/dependency_links.txt
zy_tools.egg-info/top_level.txt
zy_tools.egg-info/zip-safe