Metadata-Version: 1.1
Name: zy-tools
Version: 0.2.4
Summary: this is a tool package for zy.
Home-page: https://github.com/pypa/sampleproject
Author: John
Author-email: zyq9233@163.com
License: MIT
Keywords: zy python package for list
Platform: UNKNOWN
Classifier: License :: OSI Approved :: MIT License
Classifier: Programming Language :: Python
Classifier: Intended Audience :: Developers
Classifier: Operating System :: OS Independent
